sanitized_dump/__init__.py
sanitized_dump/config.py
sanitized_dump/models.py
sanitized_dump/management/__init__.py
sanitized_dump/management/base_commands.py
sanitized_dump/management/commands/__init__.py
sanitized_dump/management/commands/check_sanitizerconfig.py
sanitized_dump/management/commands/create_sanitized_dump.py
sanitized_dump/management/commands/init_sanitizer.py
sanitized_dump/utils/__init__.py
sanitized_dump/utils/compat.py
sanitized_dump/utils/db.py
sanitized_dump/utils/models.py
django_sanitized_dump-1.2.2.dist-info/LICENSE
django_sanitized_dump-1.2.2.dist-info/METADATA
django_sanitized_dump-1.2.2.dist-info/WHEEL
django_sanitized_dump-1.2.2.dist-info/top_level.txt
django_sanitized_dump-1.2.2.dist-info/RECORD
