Metadata-Version: 2.1
Name: django-sanitized-dump
Version: 1.2.2
Summary: Sanitized sensitive information from your database dumps
Home-page: https://github.com/andersinno/django-sanitized-dump
Maintainer: Anders Innovations
Maintainer-email: support@anders.fi
License: MIT
Keywords: django,database,sanitization,anonymization
Platform: any
Classifier: Development Status :: 3 - Alpha
Classifier: Programming Language :: Python
Classifier: Programming Language :: Python :: 2
Classifier: Programming Language :: Python :: 2.7
Classifier: Programming Language :: Python :: 3
Classifier: Programming Language :: Python :: 3.4
Classifier: Programming Language :: Python :: 3.5
Classifier: Programming Language :: Python :: 3.6
Classifier: Intended Audience :: Developers
Classifier: Intended Audience :: System Administrators
Classifier: License :: OSI Approved :: MIT License
Classifier: Operating System :: OS Independent
Classifier: Topic :: System :: Systems Administration
Requires-Dist: pyyaml
Requires-Dist: six
Requires-Dist: database-sanitizer
Provides-Extra: mysql
Requires-Dist: PyMySQL ; extra == 'mysql'
